cjy_wfy8/__init__.py
cjy_wfy8/background.jpg
cjy_wfy8/crash.wav
cjy_wfy8/font.ttf
cjy_wfy8/kaiti.ttf
cjy_wfy8/main.py
cjy_wfy8/racecar.jpg
cjy_wfy8/racestart.wav
cjy_wfy8/tiantiande.wav
cjy_wfy8/photos/1.jpg
cjy_wfy8/photos/10.jpg
cjy_wfy8/photos/11.jpg
cjy_wfy8/photos/12.jpg
cjy_wfy8/photos/13.jpg
cjy_wfy8/photos/14.jpg
cjy_wfy8/photos/15.jpg
cjy_wfy8/photos/2.jpg
cjy_wfy8/photos/3.jpg
cjy_wfy8/photos/4.jpg
cjy_wfy8/photos/5.jpg
cjy_wfy8/photos/6.jpg
cjy_wfy8/photos/7.jpg
cjy_wfy8/photos/70.jpg
cjy_wfy8/photos/8.jpg
cjy_wfy8/photos/9.jpg
cjy_wfy8-0.0.1.dist-info/LICENSE
cjy_wfy8-0.0.1.dist-info/METADATA
cjy_wfy8-0.0.1.dist-info/WHEEL
cjy_wfy8-0.0.1.dist-info/top_level.txt
cjy_wfy8-0.0.1.dist-info/RECORD
